{
	"class" : {
		"fieldsDesc" : "GlennCavarle 12/11/2016 21:03" },
	"instance" : {
		"accept:" : "GlennCavarle 12/20/2016 09:33",
		"changed_mask" : "GlennCavarle 12/11/2016 21:07",
		"changed_mask:" : "GlennCavarle 12/11/2016 21:07",
		"new_window_state" : "GlennCavarle 12/11/2016 21:07",
		"new_window_state:" : "GlennCavarle 12/11/2016 21:07",
		"send_event" : "GlennCavarle 12/11/2016 21:07",
		"send_event:" : "GlennCavarle 12/11/2016 21:07",
		"type" : "GlennCavarle 12/11/2016 21:07",
		"type:" : "GlennCavarle 12/11/2016 21:07",
		"window" : "GlennCavarle 12/11/2016 21:07",
		"window:" : "GlennCavarle 12/11/2016 21:07" } }
